gh.py
githc-0.2.2.dist-info/LICENSE.md
githc-0.2.2.dist-info/METADATA
githc-0.2.2.dist-info/WHEEL
githc-0.2.2.dist-info/entry_points.txt
githc-0.2.2.dist-info/top_level.txt
githc-0.2.2.dist-info/RECORD
